actix/__init__.py
actix/activations_tf.py
actix/activations_torch.py
actix/utils.py
actix-0.5.0.dist-info/licenses/LICENSE
actix-0.5.0.dist-info/METADATA
actix-0.5.0.dist-info/WHEEL
actix-0.5.0.dist-info/top_level.txt
actix-0.5.0.dist-info/RECORD
